<CrossIndustryInvoice xmlns:udt="urn:un:unece:uncefact:data:standard:UnqualifiedDataType:100" xmlns:ram="urn:un:unece:uncefact:data:standard:ReusableAggregateBusinessInformationEntity:100" xmlns:qdt="urn:un:unece:uncefact:data:standard:QualifiedDataType:100" xmlns:rsm="urn:un:unece:uncefact:data:standard:CrossIndustryInvoice:100">
        <ExchangedDocumentContext>
          <ram:BusinessProcessSpecifiedDocumentContextParameter>
            <ram:ID>urn:fdc:peppol.eu:2017:poacc:billing:01:1.0</ram:ID>
          </ram:BusinessProcessSpecifiedDocumentContextParameter>
          <ram:GuidelineSpecifiedDocumentContextParameter>
            <ram:ID>urn:cen.eu:en16931:2017#compliant#urn:xeinkauf.de:kosit:xrechnung_3.0</ram:ID>
          </ram:GuidelineSpecifiedDocumentContextParameter>
        </ExchangedDocumentContext>
        <ExchangedDocument>
          <ram:ID>test1</ram:ID>
          <ram:TypeCode>326</ram:TypeCode>
          <ram:IssueDateTime>
            <udt:DateTimeString format="102">2025-03-31</udt:DateTimeString>
          </ram:IssueDateTime>
        </ExchangedDocument>
      </CrossIndustryInvoice>